cli50/__init__.py
cli50/__main__.py
cli50/locale/es/LC_MESSAGES/cli50.mo
cli50/locale/es/LC_MESSAGES/cli50.po
cli50-8.0.0.dist-info/LICENSE
cli50-8.0.0.dist-info/METADATA
cli50-8.0.0.dist-info/WHEEL
cli50-8.0.0.dist-info/entry_points.txt
cli50-8.0.0.dist-info/top_level.txt
cli50-8.0.0.dist-info/RECORD
